Metadata-Version: 2.1
Name: smhi-open-data
Version: 0.0.8
Summary: Simple Python interface to the Swedish Meteorological and Hydrological Institute's (SMHI).
Home-page: https://github.com/LasseRegin/smhi-open-data
Author: Lasse Regin Nielsen
Author-email: lasseregin@gmail.com
License: UNKNOWN
Platform: UNKNOWN
Classifier: Programming Language :: Python :: 3
Classifier: License :: OSI Approved :: MIT License
Classifier: Operating System :: OS Independent
Requires-Python: >=3.6
